{
  "baseSetSize": {
    "type": "integer",
    "example": "259",
    "description": "Number of cards in the set. Will default to {{code:totalSetSize}} if not available. Note that Wizards sometimes prints extra cards beyond the set size into promos or supplemental products."
  },
  "block": {
    "type": "string",
    "example": "\"Guilds of Ravnica\"",
    "description": "Block name the set was in."
  },
  "boosterV3": {
    "type": "array(array, string)",
    "example": "[[mythic, rare], uncommon]",
    "description": "The card rarity contents of a typical booster pack."
  },
  "cards": {
    "type": "array(object)",
    "example": "{{link:card}}",
    "description": "List of cards in this set."
  },
  "code": {
    "type": "string",
    "example": "\"RNA\"",
    "description": "Set code for the set."
  },
  "codeV3": {
    "type": "string",
    "example": "\"XYZ\"",
    "description": "Alternate set code Wizards uses for a select few duel deck sets.",
    "traits": ["optional"]
  },
  "isFoilOnly": {
    "type": "boolean",
    "example": "true",
    "description": "Is the set available only in foil?",
    "traits": ["optional"]
  },
  "isOnlineOnly": {
    "type": "boolean",
    "example": "true",
    "description": "Is the set available online only?",
    "traits": ["optional"]
  },
  "keyruneCode": {
    "type": "string",
    "example": "\"KTK\"",
    "description": "The matching keyrune code for {{external:Keyrune$https://andrewgioia.github.io/Keyrune/}} image icons."
  },
  "mcmName": {
    "type": "string",
    "example": "\"Ravnica Allegiance\"",
    "description": "The Magic Card Market set name."
  },
  "mcmId": {
    "type": "integer",
    "example": "2411",
    "description": "The Magic Card Market set ID."
  },
  "meta": {
    "type": "object(string: string)",
    "example": "{{link:version}}",
    "description": "See the {{link:version}} structure."
  },
  "mtgoCode": {
    "type": "string",
    "example": "\"RNA\"",
    "description": "Set code for the set as it appears on Magic: The Gathering Online."
  },
  "name": {
    "type": "string",
    "example": "\"Ravnica Allegiance\"",
    "description": "Name of the set."
  },
  "parentCode": {
    "type": "string",
    "example": "\"RNA\"",
    "description": "The parent set code for set variations like promotions, guild kits, etc."
  },
  "releaseDate": {
    "type": "string",
    "example": "\"2019-01-25\"",
    "description": "Release date in {{external:ISO-8601$https://www.iso.org/iso-8601-date-and-time-format.html}} format for the set."
  },
  "tcgplayerGroupId": {
    "type": "integer",
    "example": "2366",
    "description": "Group ID of the set on TCGPlayer."
  },
  "tokens": {
    "type": "array(object)",
    "example": "{{link:token}}",
    "description": "Tokens available to the set. See the {{link:token}} structure."
  },
  "totalSetSize": {
    "type": "integer",
    "example": "273",
    "description": "Total number of cards in the set, including promos and related supplemental products."
  },
  "translations": {
    "type": "object(string: string)",
    "example": "{{link:translations}}",
    "description": "Translated set name by language. See the {{link:translations}} structure."
  },
  "type": {
    "type": "string",
    "example": "\"expansion\"",
    "description": "As of 03-28-2019, the possible values are {{code:archenemy}}, {{code:box}}, {{code:core}}, {{code:commander}}, {{code:draft_innovation}}, {{code:duel_deck}}, {{code:expansion}}, {{code:from_the_vault}}, {{code:funny}}, {{code:masters}}, {{code:masterpiece}}, {{code:memorabilia}}, {{code:spellbook}}, {{code:planechase}}, {{code:premium_deck}}, {{code:promo}}, {{code:starter}}, {{code:token}}, {{code:treasure_chest}} or {{code:vanguard}}",
    "traits": ["stale"]
  }
}
